npplus/__init__.py
npplus/basic.py
npplus/fermi.py
npplus/gamma.py
npplus/interactive.py
npplus/itemattr.py
npplus/lsqfit.py
npplus/pcwise.py
npplus/pwpoly.py
npplus/randomx.py
npplus/solveper.py
npplus/pyplotx/__init__.py
npplus/pyplotx/cbqcolors.py
npplus/pyplotx/interactive.py
npplus/pyplotx/mpl2cmaps.py
npplus/pyplotx/mpldefaults.py
npplus/pyplotx/pltwraps.py
npplus-0.9.8.dist-info/METADATA
npplus-0.9.8.dist-info/RECORD
npplus-0.9.8.dist-info/WHEEL
npplus-0.9.8.dist-info/top_level.txt
