Metadata-Version: 2.1
Name: npplus
Version: 0.9.8
Summary: Enhancements to Numpy
Home-page: https://github.com/dhmunro/npplus
Author: David H. Munro
Author-email: dhmunro@users.sourceforge.net
License: http://opensource.org/licenses/BSD-2-Clause
Platform: Linux
Platform: MacOS X
Platform: Unix
Classifier: License :: OSI Approved :: BSD License
Classifier: Programming Language :: Python :: 2.7
Classifier: Programming Language :: Python :: 3
Classifier: Operating System :: POSIX :: Linux
Classifier: Operating System :: MacOS :: MacOS X
Classifier: Operating System :: Unix
Requires-Dist: numpy (>=1.5.1)
Requires-Dist: scipy (>=0.9.0)
Requires-Dist: matplotlib (>=1.0.1)
